{
  "project_info": {
    "project_number": "929938752072",
    "project_id": "testebanco-88b0c",
    "storage_bucket": "testebanco-88b0c.appspot.com"
  },
  "client": [
    {
      "client_info": {
        "mobilesdk_app_id": "1:929938752072:android:7579aae8a82685ee504e7d",
        "android_client_info": {
          "package_name": "com.example.teste_banco"
        }
      },
      "oauth_client": [
        {
          "client_id": "929938752072-6ra27iqqjah0lj48vl47782jc7fogsti.apps.googleusercontent.com",
          "client_type": 3
        }
      ],
      "api_key": [
        {
          "current_key": "AIzaSyCDnEo8R0LsY9p3Ec09kUHddBbr_NSHlsY"
        }
      ],
      "services": {
        "appinvite_service": {
          "other_platform_oauth_client": [
            {
              "client_id": "929938752072-6ra27iqqjah0lj48vl47782jc7fogsti.apps.googleusercontent.com",
              "client_type": 3
            }
          ]
        }
      }
    }
  ],
  "configuration_version": "1"
}